naja/__init__.py
naja/compile_contracts.py
naja/create_workspace.py
naja/naja.py
naja_cli-0.6.dist-info/METADATA
naja_cli-0.6.dist-info/WHEEL
naja_cli-0.6.dist-info/entry_points.txt
naja_cli-0.6.dist-info/top_level.txt
naja_cli-0.6.dist-info/RECORD
