Metadata-Version: 2.1
Name: naja-cli
Version: 0.6
Summary: command line tool for vyper smart contract development
Home-page: UNKNOWN
Author: HippoB
Author-email: UNKNOWN
License: MIT
Platform: UNKNOWN
